{"is_source_file": false, "format": "", "description": "", "external_files": [], "external_methods": [], "published": [], "classes": [], "methods": [], "calls": [], "search-terms": [], "state": 2, "file_id": 4, "knowledge_revision": 7, "git_revision": "622edd6913b69d10c902c43eb088d2400d6df6aa", "hash": "095fad4071a08d706a80ae7fb859a1fe", "format-version": 4, "code-base-name": "resident_directory_backend", "filename": "README.md", "revision_history": [{"7": "622edd6913b69d10c902c43eb088d2400d6df6aa"}]}